modelfeast/__init__.py
modelfeast/classifier.py
modelfeast/train.py
modelfeast/base/__init__.py
modelfeast/base/base_data_loader.py
modelfeast/base/base_model.py
modelfeast/base/base_trainer.py
modelfeast/data_loader/__init__.py
modelfeast/data_loader/data_loaders.py
modelfeast/models/__init__.py
modelfeast/models/loss.py
modelfeast/models/metric.py
modelfeast/models/model_template.py
modelfeast/models/StereoCNN/Densenet_module.py
modelfeast/models/StereoCNN/I3D_module.py
modelfeast/models/StereoCNN/Resnet_module.py
modelfeast/models/StereoCNN/Resnetv2_module.py
modelfeast/models/StereoCNN/Resnext_module.py
modelfeast/models/StereoCNN/WideResnet_module.py
modelfeast/models/StereoCNN/__init__.py
modelfeast/models/StereoCNN/densenet.py
modelfeast/models/StereoCNN/i3d.py
modelfeast/models/StereoCNN/resnet.py
modelfeast/models/StereoCNN/resnetv2.py
modelfeast/models/StereoCNN/resnext.py
modelfeast/models/StereoCNN/wideresnet.py
modelfeast/models/classifiers/DenseNet_module.py
modelfeast/models/classifiers/Inception_module.py
modelfeast/models/classifiers/InceptionresnetV2_module.py
modelfeast/models/classifiers/ResNet_module.py
modelfeast/models/classifiers/ResNext101_module.py
modelfeast/models/classifiers/ResNext101_module2.py
modelfeast/models/classifiers/Squeezenet_module.py
modelfeast/models/classifiers/Vgg_module.py
modelfeast/models/classifiers/Xception_module.py
modelfeast/models/classifiers/__init__.py
modelfeast/models/classifiers/densenet.py
modelfeast/models/classifiers/inception.py
modelfeast/models/classifiers/inceptionresnetv2.py
modelfeast/models/classifiers/resnet.py
modelfeast/models/classifiers/resnext.py
modelfeast/models/classifiers/squeezenet.py
modelfeast/models/classifiers/vgg.py
modelfeast/models/classifiers/xception.py
modelfeast/trainer/__init__.py
modelfeast/trainer/trainer.py
modelfeast/utils/__init__.py
modelfeast/utils/logger.py
modelfeast/utils/util.py
modelfeast/utils/visualization.py
modelfeast-0.1.5.dist-info/DESCRIPTION.rst
modelfeast-0.1.5.dist-info/METADATA
modelfeast-0.1.5.dist-info/RECORD
modelfeast-0.1.5.dist-info/WHEEL
modelfeast-0.1.5.dist-info/metadata.json
modelfeast-0.1.5.dist-info/top_level.txt
