Metadata-Version: 2.0
Name: modelfeast
Version: 0.1.5
Summary: Pytorch model zoo
Home-page: https://github.com/daili0015/ModelFeast
Author: Chengyao Zheng
Author-email: daili0015@gmail.com
License: MIT License
Platform: all
Classifier: License :: OSI Approved :: MIT License
Classifier: Intended Audience :: Developers
Classifier: Operating System :: OS Independent
Classifier: Programming Language :: Python
Classifier: Programming Language :: Python :: 3
Classifier: Programming Language :: Python :: 3.3
Classifier: Programming Language :: Python :: 3.4
Classifier: Programming Language :: Python :: 3.5
Requires-Dist: numpy (>=1.10.0)
Requires-Dist: torch (>=0.4.0)
